xl_durel_utils/__init__.py
xl_durel_utils/core.py
xl_durel_utils-1.0.4.dist-info/licenses/LICENSE
xl_durel_utils-1.0.4.dist-info/METADATA
xl_durel_utils-1.0.4.dist-info/WHEEL
xl_durel_utils-1.0.4.dist-info/top_level.txt
xl_durel_utils-1.0.4.dist-info/RECORD
